facet/__init__.py
facet/cli.py
facet/errors.py
facet/lenses.py
facet/parser.py
facet_lang-1.0.1.dist-info/licenses/LICENSE
facet_lang-1.0.1.dist-info/METADATA
facet_lang-1.0.1.dist-info/WHEEL
facet_lang-1.0.1.dist-info/entry_points.txt
facet_lang-1.0.1.dist-info/top_level.txt
facet_lang-1.0.1.dist-info/RECORD
