Metadata-Version: 2.4
Name: facet-lang
Version: 1.0.1
Summary: FACET v1.0 — Deterministic markup for AI instructions
Project-URL: Homepage, https://github.com/rokoss21/FACET
Project-URL: Documentation, https://facet-lang.readthedocs.io/
Project-URL: Repository, https://github.com/rokoss21/FACET
Project-URL: Issues, https://github.com/rokoss21/FACET/issues
Project-URL: Changelog, https://github.com/rokoss21/FACET/blob/main/CHANGELOG.md
License-File: LICENSE
Provides-Extra: dev
Requires-Dist: pytest>=7.0; extra == "dev"
Requires-Dist: pytest-cov; extra == "dev"
Requires-Dist: black; extra == "dev"
Requires-Dist: isort; extra == "dev"
Requires-Dist: flake8; extra == "dev"
Requires-Dist: mypy; extra == "dev"
Requires-Dist: pre-commit; extra == "dev"
Provides-Extra: docs
Requires-Dist: mkdocs-material; extra == "docs"
Requires-Dist: mkdocs-mermaid2-plugin; extra == "docs"
Provides-Extra: all
Requires-Dist: facet-lang[dev,docs]; extra == "all"
Dynamic: license-file
